{
  "data": [
    {
      "date": "2020-07-05T23:59:59.999Z",
      "total": {
        "totalConfirmed": 44800,
        "totalDeaths": 26,
        "totalRecovered": 40441
      }
    },
    {
      "date": "2020-07-04T23:59:59.999Z",
      "total": {
        "totalConfirmed": 44664,
        "totalDeaths": 26,
        "totalRecovered": 40117
      }
    },
    {
      "date": "2020-07-03T23:59:59.999Z",
      "total": {
        "totalConfirmed": 44479,
        "totalDeaths": 26,
        "totalRecovered": 39769
      }
    },
    {
      "date": "2020-07-02T23:59:59.999Z",
      "total": {
        "totalConfirmed": 44310,
        "totalDeaths": 26,
        "totalRecovered": 39429
      }
    },
    {
      "date": "2020-07-01T23:59:59.999Z",
      "total": {
        "totalConfirmed": 44122,
        "totalDeaths": 26,
        "totalRecovered": 39011
      }
    },
    {
      "date": "2020-06-30T23:59:59.999Z",
      "total": {
        "totalConfirmed": 43907,
        "totalDeaths": 26,
        "totalRecovered": 38500
      }
    },
    {
      "date": "2020-06-29T23:59:59.999Z",
      "total": {
        "totalConfirmed": 43661,
        "totalDeaths": 26,
        "totalRecovered": 37985
      }
    },
    {
      "date": "2020-06-28T23:59:59.999Z",
      "total": {
        "totalConfirmed": 43459,
        "totalDeaths": 26,
        "totalRecovered": 37508
      }
    },
    {
      "date": "2020-06-27T23:59:59.999Z",
      "total": {
        "totalConfirmed": 43246,
        "totalDeaths": 26,
        "totalRecovered": 37163
      }
    },
    {
      "date": "2020-06-26T23:59:59.999Z",
      "total": {
        "totalConfirmed": 42955,
        "totalDeaths": 26,
        "totalRecovered": 36825
      }
    },
    {
      "date": "2020-06-25T23:59:59.999Z",
      "total": {
        "totalConfirmed": 42736,
        "totalDeaths": 26,
        "totalRecovered": 36604
      }
    },
    {
      "date": "2020-06-24T23:59:59.999Z",
      "total": {
        "totalConfirmed": 42623,
        "totalDeaths": 26,
        "totalRecovered": 36299
      }
    },
    {
      "date": "2020-06-23T23:59:59.999Z",
      "total": {
        "totalConfirmed": 42432,
        "totalDeaths": 26,
        "totalRecovered": 35995
      }
    },
    {
      "date": "2020-06-22T23:59:59.999Z",
      "total": {
        "totalConfirmed": 42313,
        "totalDeaths": 26,
        "totalRecovered": 35590
      }
    },
    {
      "date": "2020-06-21T23:59:59.999Z",
      "total": {
        "totalConfirmed": 42095,
        "totalDeaths": 26,
        "totalRecovered": 34942
      }
    },
    {
      "date": "2020-06-20T23:59:59.999Z",
      "total": {
        "totalConfirmed": 41833,
        "totalDeaths": 26,
        "totalRecovered": 34224
      }
    },
    {
      "date": "2020-06-19T23:59:59.999Z",
      "total": {
        "totalConfirmed": 41615,
        "totalDeaths": 26,
        "totalRecovered": 33459
      }
    },
    {
      "date": "2020-06-18T23:59:59.999Z",
      "total": {
        "totalConfirmed": 41473,
        "totalDeaths": 26,
        "totalRecovered": 32712
      }
    },
    {
      "date": "2020-06-17T23:59:59.999Z",
      "total": {
        "totalConfirmed": 41216,
        "totalDeaths": 26,
        "totalRecovered": 31938
      }
    },
    {
      "date": "2020-06-16T23:59:59.999Z",
      "total": {
        "totalConfirmed": 40969,
        "totalDeaths": 26,
        "totalRecovered": 31163
      }
    },
    {
      "date": "2020-06-15T23:59:59.999Z",
      "total": {
        "totalConfirmed": 40818,
        "totalDeaths": 26,
        "totalRecovered": 30366
      }
    },
    {
      "date": "2020-06-14T23:59:59.999Z",
      "total": {
        "totalConfirmed": 40604,
        "totalDeaths": 26,
        "totalRecovered": 29589
      }
    },
    {
      "date": "2020-06-13T23:59:59.999Z",
      "total": {
        "totalConfirmed": 40197,
        "totalDeaths": 26,
        "totalRecovered": 28808
      }
    },
    {
      "date": "2020-06-12T23:59:59.999Z",
      "total": {
        "totalConfirmed": 39850,
        "totalDeaths": 25,
        "totalRecovered": 28040
      }
    },
    {
      "date": "2020-06-11T23:59:59.999Z",
      "total": {
        "totalConfirmed": 39387,
        "totalDeaths": 25,
        "totalRecovered": 27286
      }
    },
    {
      "date": "2020-06-10T23:59:59.999Z",
      "total": {
        "totalConfirmed": 38965,
        "totalDeaths": 25,
        "totalRecovered": 26532
      }
    },
    {
      "date": "2020-06-09T23:59:59.999Z",
      "total": {
        "totalConfirmed": 38514,
        "totalDeaths": 25,
        "totalRecovered": 25877
      }
    },
    {
      "date": "2020-06-08T23:59:59.999Z",
      "total": {
        "totalConfirmed": 38296,
        "totalDeaths": 25,
        "totalRecovered": 25368
      }
    },
    {
      "date": "2020-06-07T23:59:59.999Z",
      "total": {
        "totalConfirmed": 37910,
        "totalDeaths": 25,
        "totalRecovered": 24886
      }
    },
    {
      "date": "2020-06-06T23:59:59.999Z",
      "total": {
        "totalConfirmed": 37527,
        "totalDeaths": 25,
        "totalRecovered": 24559
      }
    },
    {
      "date": "2020-06-05T23:59:59.999Z",
      "total": {
        "totalConfirmed": 37183,
        "totalDeaths": 24,
        "totalRecovered": 24209
      }
    },
    {
      "date": "2020-06-04T23:59:59.999Z",
      "total": {
        "totalConfirmed": 36922,
        "totalDeaths": 24,
        "totalRecovered": 23904
      }
    },
    {
      "date": "2020-06-03T23:59:59.999Z",
      "total": {
        "totalConfirmed": 36405,
        "totalDeaths": 24,
        "totalRecovered": 23582
      }
    },
    {
      "date": "2020-06-02T23:59:59.999Z",
      "total": {
        "totalConfirmed": 35836,
        "totalDeaths": 24,
        "totalRecovered": 23175
      }
    },
    {
      "date": "2020-06-01T23:59:59.999Z",
      "total": {
        "totalConfirmed": 35292,
        "totalDeaths": 24,
        "totalRecovered": 22466
      }
    },
    {
      "date": "2020-05-31T23:59:59.999Z",
      "total": {
        "totalConfirmed": 34884,
        "totalDeaths": 23,
        "totalRecovered": 21699
      }
    },
    {
      "date": "2020-05-30T23:59:59.999Z",
      "total": {
        "totalConfirmed": 34366,
        "totalDeaths": 23,
        "totalRecovered": 20727
      }
    },
    {
      "date": "2020-05-29T23:59:59.999Z",
      "total": {
        "totalConfirmed": 33860,
        "totalDeaths": 23,
        "totalRecovered": 19631
      }
    },
    {
      "date": "2020-05-28T23:59:59.999Z",
      "total": {
        "totalConfirmed": 33249,
        "totalDeaths": 23,
        "totalRecovered": 18294
      }
    },
    {
      "date": "2020-05-27T23:59:59.999Z",
      "total": {
        "totalConfirmed": 32876,
        "totalDeaths": 23,
        "totalRecovered": 17276
      }
    },
    {
      "date": "2020-05-26T23:59:59.999Z",
      "total": {
        "totalConfirmed": 32343,
        "totalDeaths": 23,
        "totalRecovered": 16444
      }
    },
    {
      "date": "2020-05-25T23:59:59.999Z",
      "total": {
        "totalConfirmed": 31960,
        "totalDeaths": 23,
        "totalRecovered": 15738
      }
    },
    {
      "date": "2020-05-24T23:59:59.999Z",
      "total": {
        "totalConfirmed": 31616,
        "totalDeaths": 23,
        "totalRecovered": 14876
      }
    },
    {
      "date": "2020-05-23T23:59:59.999Z",
      "total": {
        "totalConfirmed": 31068,
        "totalDeaths": 23,
        "totalRecovered": 13882
      }
    },
    {
      "date": "2020-05-22T23:59:59.999Z",
      "total": {
        "totalConfirmed": 30426,
        "totalDeaths": 23,
        "totalRecovered": 12995
      }
    },
    {
      "date": "2020-05-21T23:59:59.999Z",
      "total": {
        "totalConfirmed": 29812,
        "totalDeaths": 23,
        "totalRecovered": 12117
      }
    },
    {
      "date": "2020-05-20T23:59:59.999Z",
      "total": {
        "totalConfirmed": 29364,
        "totalDeaths": 22,
        "totalRecovered": 11207
      }
    },
    {
      "date": "2020-05-19T23:59:59.999Z",
      "total": {
        "totalConfirmed": 28794,
        "totalDeaths": 22,
        "totalRecovered": 10365
      }
    },
    {
      "date": "2020-05-18T23:59:59.999Z",
      "total": {
        "totalConfirmed": 28343,
        "totalDeaths": 22,
        "totalRecovered": 9835
      }
    },
    {
      "date": "2020-05-17T23:59:59.999Z",
      "total": {
        "totalConfirmed": 28038,
        "totalDeaths": 22,
        "totalRecovered": 9340
      }
    },
    {
      "date": "2020-05-16T23:59:59.999Z",
      "total": {
        "totalConfirmed": 27356,
        "totalDeaths": 22,
        "totalRecovered": 8342
      }
    },
    {
      "date": "2020-05-15T23:59:59.999Z",
      "total": {
        "totalConfirmed": 26891,
        "totalDeaths": 21,
        "totalRecovered": 7248
      }
    },
    {
      "date": "2020-05-14T23:59:59.999Z",
      "total": {
        "totalConfirmed": 26098,
        "totalDeaths": 21,
        "totalRecovered": 5973
      }
    },
    {
      "date": "2020-05-13T23:59:59.999Z",
      "total": {
        "totalConfirmed": 25346,
        "totalDeaths": 21,
        "totalRecovered": 4809
      }
    },
    {
      "date": "2020-05-12T23:59:59.999Z",
      "total": {
        "totalConfirmed": 24671,
        "totalDeaths": 21,
        "totalRecovered": 3851
      }
    },
    {
      "date": "2020-05-11T23:59:59.999Z",
      "total": {
        "totalConfirmed": 23822,
        "totalDeaths": 21,
        "totalRecovered": 3225
      }
    },
    {
      "date": "2020-05-10T23:59:59.999Z",
      "total": {
        "totalConfirmed": 23336,
        "totalDeaths": 20,
        "totalRecovered": 2721
      }
    },
    {
      "date": "2020-05-09T23:59:59.999Z",
      "total": {
        "totalConfirmed": 22460,
        "totalDeaths": 20,
        "totalRecovered": 2296
      }
    },
    {
      "date": "2020-05-08T23:59:59.999Z",
      "total": {
        "totalConfirmed": 21707,
        "totalDeaths": 20,
        "totalRecovered": 2040
      }
    },
    {
      "date": "2020-05-07T23:59:59.999Z",
      "total": {
        "totalConfirmed": 20939,
        "totalDeaths": 20,
        "totalRecovered": 1712
      }
    },
    {
      "date": "2020-05-06T23:59:59.999Z",
      "total": {
        "totalConfirmed": 20198,
        "totalDeaths": 20,
        "totalRecovered": 1634
      }
    },
    {
      "date": "2020-05-05T23:59:59.999Z",
      "total": {
        "totalConfirmed": 19410,
        "totalDeaths": 18,
        "totalRecovered": 1519
      }
    },
    {
      "date": "2020-05-04T23:59:59.999Z",
      "total": {
        "totalConfirmed": 18778,
        "totalDeaths": 18,
        "totalRecovered": 1457
      }
    },
    {
      "date": "2020-05-03T23:59:59.999Z",
      "total": {
        "totalConfirmed": 18205,
        "totalDeaths": 18,
        "totalRecovered": 1408
      }
    },
    {
      "date": "2020-05-02T23:59:59.999Z",
      "total": {
        "totalConfirmed": 17548,
        "totalDeaths": 17,
        "totalRecovered": 1347
      }
    },
    {
      "date": "2020-05-01T23:59:59.999Z",
      "total": {
        "totalConfirmed": 17101,
        "totalDeaths": 16,
        "totalRecovered": 1268
      }
    },
    {
      "date": "2020-04-30T23:59:59.999Z",
      "total": {
        "totalConfirmed": 16169,
        "totalDeaths": 15,
        "totalRecovered": 1244
      }
    },
    {
      "date": "2020-04-29T23:59:59.999Z",
      "total": {
        "totalConfirmed": 15641,
        "totalDeaths": 14,
        "totalRecovered": 1188
      }
    },
    {
      "date": "2020-04-28T23:59:59.999Z",
      "total": {
        "totalConfirmed": 14951,
        "totalDeaths": 14,
        "totalRecovered": 1128
      }
    },
    {
      "date": "2020-04-27T23:59:59.999Z",
      "total": {
        "totalConfirmed": 14423,
        "totalDeaths": 14,
        "totalRecovered": 1095
      }
    },
    {
      "date": "2020-04-26T23:59:59.999Z",
      "total": {
        "totalConfirmed": 13624,
        "totalDeaths": 12,
        "totalRecovered": 1060
      }
    },
    {
      "date": "2020-04-25T23:59:59.999Z",
      "total": {
        "totalConfirmed": 12693,
        "totalDeaths": 12,
        "totalRecovered": 1002
      }
    },
    {
      "date": "2020-04-24T23:59:59.999Z",
      "total": {
        "totalConfirmed": 12075,
        "totalDeaths": 12,
        "totalRecovered": 956
      }
    },
    {
      "date": "2020-04-23T23:59:59.999Z",
      "total": {
        "totalConfirmed": 11178,
        "totalDeaths": 12,
        "totalRecovered": 924
      }
    },
    {
      "date": "2020-04-22T23:59:59.999Z",
      "total": {
        "totalConfirmed": 10141,
        "totalDeaths": 12,
        "totalRecovered": 896
      }
    },
    {
      "date": "2020-04-21T23:59:59.999Z",
      "total": {
        "totalConfirmed": 9125,
        "totalDeaths": 11,
        "totalRecovered": 839
      }
    },
    {
      "date": "2020-04-20T23:59:59.999Z",
      "total": {
        "totalConfirmed": 8014,
        "totalDeaths": 11,
        "totalRecovered": 801
      }
    },
    {
      "date": "2020-04-19T23:59:59.999Z",
      "total": {
        "totalConfirmed": 6588,
        "totalDeaths": 11,
        "totalRecovered": 768
      }
    },
    {
      "date": "2020-04-18T23:59:59.999Z",
      "total": {
        "totalConfirmed": 5992,
        "totalDeaths": 11,
        "totalRecovered": 740
      }
    },
    {
      "date": "2020-04-17T23:59:59.999Z",
      "total": {
        "totalConfirmed": 5050,
        "totalDeaths": 11,
        "totalRecovered": 708
      }
    },
    {
      "date": "2020-04-16T23:59:59.999Z",
      "total": {
        "totalConfirmed": 4427,
        "totalDeaths": 10,
        "totalRecovered": 683
      }
    },
    {
      "date": "2020-04-15T23:59:59.999Z",
      "total": {
        "totalConfirmed": 3699,
        "totalDeaths": 10,
        "totalRecovered": 652
      }
    },
    {
      "date": "2020-04-14T23:59:59.999Z",
      "total": {
        "totalConfirmed": 3252,
        "totalDeaths": 10,
        "totalRecovered": 611
      }
    },
    {
      "date": "2020-04-13T23:59:59.999Z",
      "total": {
        "totalConfirmed": 2918,
        "totalDeaths": 9,
        "totalRecovered": 586
      }
    },
    {
      "date": "2020-04-12T23:59:59.999Z",
      "total": {
        "totalConfirmed": 2532,
        "totalDeaths": 8,
        "totalRecovered": 560
      }
    },
    {
      "date": "2020-04-11T23:59:59.999Z",
      "total": {
        "totalConfirmed": 2299,
        "totalDeaths": 8,
        "totalRecovered": 528
      }
    },
    {
      "date": "2020-04-10T23:59:59.999Z",
      "total": {
        "totalConfirmed": 2108,
        "totalDeaths": 7,
        "totalRecovered": 492
      }
    },
    {
      "date": "2020-04-09T23:59:59.999Z",
      "total": {
        "totalConfirmed": 1910,
        "totalDeaths": 6,
        "totalRecovered": 460
      }
    },
    {
      "date": "2020-04-08T23:59:59.999Z",
      "total": {
        "totalConfirmed": 1623,
        "totalDeaths": 6,
        "totalRecovered": 406
      }
    },
    {
      "date": "2020-04-07T23:59:59.999Z",
      "total": {
        "totalConfirmed": 1481,
        "totalDeaths": 6,
        "totalRecovered": 377
      }
    },
    {
      "date": "2020-04-06T23:59:59.999Z",
      "total": {
        "totalConfirmed": 1375,
        "totalDeaths": 6,
        "totalRecovered": 344
      }
    },
    {
      "date": "2020-04-05T23:59:59.999Z",
      "total": {
        "totalConfirmed": 1309,
        "totalDeaths": 6,
        "totalRecovered": 320
      }
    },
    {
      "date": "2020-04-04T23:59:59.999Z",
      "total": {
        "totalConfirmed": 1189,
        "totalDeaths": 6,
        "totalRecovered": 297
      }
    },
    {
      "date": "2020-04-03T23:59:59.999Z",
      "total": {
        "totalConfirmed": 1114,
        "totalDeaths": 5,
        "totalRecovered": 282
      }
    },
    {
      "date": "2020-04-02T23:59:59.999Z",
      "total": {
        "totalConfirmed": 1049,
        "totalDeaths": 4,
        "totalRecovered": 266
      }
    },
    {
      "date": "2020-04-01T23:59:59.999Z",
      "total": {
        "totalConfirmed": 1000,
        "totalDeaths": 3,
        "totalRecovered": 245
      }
    },
    {
      "date": "2020-03-31T23:59:59.999Z",
      "total": {
        "totalConfirmed": 926,
        "totalDeaths": 3,
        "totalRecovered": 240
      }
    },
    {
      "date": "2020-03-30T23:59:59.999Z",
      "total": {
        "totalConfirmed": 879,
        "totalDeaths": 3,
        "totalRecovered": 228
      }
    },
    {
      "date": "2020-03-29T23:59:59.999Z",
      "total": {
        "totalConfirmed": 844,
        "totalDeaths": 3,
        "totalRecovered": 212
      }
    },
    {
      "date": "2020-03-28T23:59:59.999Z",
      "total": {
        "totalConfirmed": 802,
        "totalDeaths": 2,
        "totalRecovered": 198
      }
    },
    {
      "date": "2020-03-27T23:59:59.999Z",
      "total": {
        "totalConfirmed": 732,
        "totalDeaths": 2,
        "totalRecovered": 183
      }
    },
    {
      "date": "2020-03-26T23:59:59.999Z",
      "total": {
        "totalConfirmed": 683,
        "totalDeaths": 2,
        "totalRecovered": 172
      }
    },
    {
      "date": "2020-03-25T23:59:59.999Z",
      "total": {
        "totalConfirmed": 631,
        "totalDeaths": 2,
        "totalRecovered": 160
      }
    },
    {
      "date": "2020-03-24T23:59:59.999Z",
      "total": {
        "totalConfirmed": 558,
        "totalDeaths": 2,
        "totalRecovered": 156
      }
    },
    {
      "date": "2020-03-23T23:59:59.999Z",
      "total": {
        "totalConfirmed": 509,
        "totalDeaths": 2,
        "totalRecovered": 152
      }
    },
    {
      "date": "2020-03-22T23:59:59.999Z",
      "total": {
        "totalConfirmed": 455,
        "totalDeaths": 2,
        "totalRecovered": 144
      }
    },
    {
      "date": "2020-03-21T23:59:59.999Z",
      "total": {
        "totalConfirmed": 432,
        "totalDeaths": 2,
        "totalRecovered": 140
      }
    },
    {
      "date": "2020-03-20T23:59:59.999Z",
      "total": {
        "totalConfirmed": 385,
        "totalDeaths": 0,
        "totalRecovered": 124
      }
    },
    {
      "date": "2020-03-19T23:59:59.999Z",
      "total": {
        "totalConfirmed": 345,
        "totalDeaths": 0,
        "totalRecovered": 114
      }
    },
    {
      "date": "2020-03-18T23:59:59.999Z",
      "total": {
        "totalConfirmed": 313,
        "totalDeaths": 0,
        "totalRecovered": 114
      }
    },
    {
      "date": "2020-03-17T23:59:59.999Z",
      "total": {
        "totalConfirmed": 266,
        "totalDeaths": 0,
        "totalRecovered": 114
      }
    },
    {
      "date": "2020-03-16T23:59:59.999Z",
      "total": {
        "totalConfirmed": 243,
        "totalDeaths": 0,
        "totalRecovered": 109
      }
    },
    {
      "date": "2020-03-15T23:59:59.999Z",
      "total": {
        "totalConfirmed": 226,
        "totalDeaths": 0,
        "totalRecovered": 105
      }
    },
    {
      "date": "2020-03-14T23:59:59.999Z",
      "total": {
        "totalConfirmed": 212,
        "totalDeaths": 0,
        "totalRecovered": 105
      }
    },
    {
      "date": "2020-03-13T23:59:59.999Z",
      "total": { "totalConfirmed": 200, "totalDeaths": 0, "totalRecovered": 97 }
    },
    {
      "date": "2020-03-12T23:59:59.999Z",
      "total": { "totalConfirmed": 178, "totalDeaths": 0, "totalRecovered": 96 }
    },
    {
      "date": "2020-03-11T23:59:59.999Z",
      "total": { "totalConfirmed": 178, "totalDeaths": 0, "totalRecovered": 96 }
    },
    {
      "date": "2020-03-10T23:59:59.999Z",
      "total": { "totalConfirmed": 160, "totalDeaths": 0, "totalRecovered": 78 }
    },
    {
      "date": "2020-03-09T23:59:59.999Z",
      "total": { "totalConfirmed": 150, "totalDeaths": 0, "totalRecovered": 78 }
    },
    {
      "date": "2020-03-08T23:59:59.999Z",
      "total": { "totalConfirmed": 150, "totalDeaths": 0, "totalRecovered": 78 }
    },
    {
      "date": "2020-03-07T23:59:59.999Z",
      "total": { "totalConfirmed": 138, "totalDeaths": 0, "totalRecovered": 78 }
    },
    {
      "date": "2020-03-06T23:59:59.999Z",
      "total": { "totalConfirmed": 130, "totalDeaths": 0, "totalRecovered": 78 }
    },
    {
      "date": "2020-03-05T23:59:59.999Z",
      "total": { "totalConfirmed": 117, "totalDeaths": 0, "totalRecovered": 78 }
    },
    {
      "date": "2020-03-04T23:59:59.999Z",
      "total": { "totalConfirmed": 110, "totalDeaths": 0, "totalRecovered": 78 }
    },
    {
      "date": "2020-03-03T23:59:59.999Z",
      "total": { "totalConfirmed": 110, "totalDeaths": 0, "totalRecovered": 78 }
    },
    {
      "date": "2020-03-02T23:59:59.999Z",
      "total": { "totalConfirmed": 108, "totalDeaths": 0, "totalRecovered": 78 }
    },
    {
      "date": "2020-03-01T23:59:59.999Z",
      "total": { "totalConfirmed": 106, "totalDeaths": 0, "totalRecovered": 72 }
    }
  ],
  "country": "SG"
}
